smart_open_with_pbgzip/__init__.py
smart_open_with_pbgzip-0.1.5.dist-info/METADATA
smart_open_with_pbgzip-0.1.5.dist-info/WHEEL
smart_open_with_pbgzip-0.1.5.dist-info/RECORD
