Metadata-Version: 2.1
Name: smart-open-with-pbgzip
Version: 0.1.5
Summary: Makes smart_open write to .gz/.gzip files using pbgzip rather than gzip
License: MIT
Author: Ben Skubi
Author-email: bskubi@gmail.com
Requires-Python: >=3.10,<4.0
Classifier: License :: OSI Approved :: MIT License
Classifier: Programming Language :: Python :: 3
Classifier: Programming Language :: Python :: 3.10
Classifier: Programming Language :: Python :: 3.11
Classifier: Programming Language :: Python :: 3.12
Requires-Dist: smart-open (>=7.0.4,<8.0.0)
